{
	"id": "HYBRV1nlLthalyG",
	"json": "{\"id\":\"HYBRV1nlLthalyG\",\"url\":\"https://winmart.vn/products/vim-toilet-xanh-bien-880ml--s10170676?storeGroupCode=1998&storeCode=1535\",\"uniqueKey\":\"https://winmart.vn/products/vim-toilet-xanh-bien-880ml--s10170676?storeCode=1535&storeGroupCode=1998\",\"method\":\"GET\",\"noRetry\":false,\"retryCount\":0,\"errorMessages\":[],\"headers\":{},\"userData\":{\"label\":\"DETAIL_OR_CATEGORY\",\"__crawlee\":{\"crawlDepth\":2}}}",
	"method": "GET",
	"orderNo": 1782494319652,
	"retryCount": 0,
	"uniqueKey": "https://winmart.vn/products/vim-toilet-xanh-bien-880ml--s10170676?storeCode=1535&storeGroupCode=1998",
	"url": "https://winmart.vn/products/vim-toilet-xanh-bien-880ml--s10170676?storeGroupCode=1998&storeCode=1535"
}