{
	"id": "kc1kPD5enw98i8U",
	"json": "{\"id\":\"kc1kPD5enw98i8U\",\"url\":\"https://winmart.vn/products/wmnk-cherry-do-my--s10140386?storeGroupCode=1998&storeCode=1535\",\"uniqueKey\":\"https://winmart.vn/products/wmnk-cherry-do-my--s10140386?storeCode=1535&storeGroupCode=1998\",\"method\":\"GET\",\"noRetry\":false,\"retryCount\":0,\"errorMessages\":[],\"headers\":{},\"userData\":{\"label\":\"DETAIL_OR_CATEGORY\",\"__crawlee\":{\"crawlDepth\":2}}}",
	"method": "GET",
	"orderNo": 1782494308849,
	"retryCount": 0,
	"uniqueKey": "https://winmart.vn/products/wmnk-cherry-do-my--s10140386?storeCode=1535&storeGroupCode=1998",
	"url": "https://winmart.vn/products/wmnk-cherry-do-my--s10140386?storeGroupCode=1998&storeCode=1535"
}